hexanonyme/__init__.py
hexanonyme/core/__init__.py
hexanonyme/core/anonymizer/__init__.py
hexanonyme/core/anonymizer/base_anonymizer.py
hexanonyme/core/anonymizer/redact_anonymizer.py
hexanonyme/core/anonymizer/replace_anonymizer.py
tests/__init__.py
tests/test_redact_anonymizer.py
tests/test_replace_anonymizer.py
hexanonyme-0.1.2.dist-info/LICENSE
hexanonyme-0.1.2.dist-info/METADATA
hexanonyme-0.1.2.dist-info/WHEEL
hexanonyme-0.1.2.dist-info/top_level.txt
hexanonyme-0.1.2.dist-info/RECORD
