Metadata-Version: 2.1
Name: hexanonyme
Version: 0.1.2
Summary: A Python package for PII data anonymization
Home-page: https://github.com/BirdiD/hexanonyme
Author: Dioula DOUCOURE
Author-email: diioula.doucoure@gmail.com
License: MIT
Classifier: Intended Audience :: Developers
Classifier: License :: OSI Approved :: MIT License
Classifier: Natural Language :: English
Classifier: Operating System :: OS Independent
Classifier: Programming Language :: Python :: 3
Classifier: Programming Language :: Python :: 3.6
Classifier: Programming Language :: Python :: 3.7
Classifier: Programming Language :: Python :: 3.8
Classifier: Programming Language :: Python :: 3.9
License-File: LICENSE
Requires-Dist: transformers >=4.32.1
Requires-Dist: sentencepiece >=0.1.99
Requires-Dist: faker >=19.3.1
Requires-Dist: torch >=2.0.1
